rmbi3110
