Metadata-Version: 2.1
Name: rmbi3110
Version: 1.2.10
Summary: Do not distribute it without permission. 
Author: Xuhu Wan
Author-email: xuhu.wan@gmail.com
Requires-Dist: numpy
Requires-Dist: pandas
Requires-Dist: plotly
Requires-Dist: yfinance
Requires-Dist: statsmodels
